nimRum/__init__.py
nimRum/gitStatus.txt
nimRum/libNimRumAlsaCapture_py.so
nimRum/libNimRumRx_py.so
nimRum/libNimRumTx_py.so
nimRum/nimRumCheckHW.py
nimRum/nimRumMeasSpikes.py
nimRum/nimRumMeasure.py
nimRum/nimRumPyCommon.py
nimRum/nimRumPyLed.py
nimRum/nimRumRotaryEnc.py
nimRum/nimRumRx.py
nimRum/nimRumRxCfg.py
nimRum/nimRumRxVolumeConversion.py
nimRum/nimRumToneGen.py
nimRum/nimRumTx.py
nimRum/nimRumTxCfg.py
nimRum/nimRumTxReadFile_soundfile.py
nimRum/nimRumTxReadFile_wavio.py
nimRum/nimRumTxRemote.py
nimRum/nonBlockingConsole.py
nimRum/runNimRumForever.py
nimRum/runNimRumRx.py
nimRum/runNimRumTx.py
nimRum/txConfig.yaml
nimrum-1.1.2.dist-info/METADATA
nimrum-1.1.2.dist-info/WHEEL
nimrum-1.1.2.dist-info/entry_points.txt
nimrum-1.1.2.dist-info/licenses/LICENSE.txt
nimrum-1.1.2.dist-info/RECORD
