Metadata-Version: 2.4
Name: nimRum
Version: 1.1.2
Summary: Nimble Rumble, a library to play wireless(WiFi) sound in perfect synch, for private use and evaluation
Project-URL: Homepage, https://www.abtaudio.tech/
Author-email: AbtAudio AB <evaluate@abtaudio.tech>
Maintainer-email: AbtAudio AB <evaluate@abtaudio.tech>
License: /*-----------------------------------------------------------------------------
License-File: LICENSE.txt
Keywords: about time audio,abtaudio,synchronization,wireless audio
Classifier: Development Status :: 5 - Production/Stable
Classifier: License :: Other/Proprietary License
Classifier: Operating System :: POSIX
Classifier: Programming Language :: C
Classifier: Programming Language :: Python :: 3
Classifier: Topic :: Multimedia :: Sound/Audio
Classifier: Topic :: Software Development :: Embedded Systems
Requires-Python: >=3.9
Requires-Dist: gpiozero
Requires-Dist: lirc
Requires-Dist: netifaces
Requires-Dist: numpy
Requires-Dist: pyyaml
Requires-Dist: rpi-gpio
Requires-Dist: sounddevice
Requires-Dist: soundfile
Requires-Dist: wavio
